{
  "ecs7": true,
  "display": {
    "title": "Decentraland Playground ECS7 Scene",
    "description": "",
    "navmapThumbnail": "images/scene-thumbnail.png",
    "favicon": "favicon_asset"
  },
  "owner": "",
  "contact": {
    "name": "SDK",
    "email": ""
  },
  "main": "dist/scene.js",
  "tags": [],
  "scene": {
    "parcels": [
      "0,0"
    ],
    "base": "0,0"
  },
  "spawnPoints": [
    {
      "name": "spawn1",
      "default": true,
      "position": {
        "x": 0,
        "y": 0,
        "z": 0
      },
      "cameraTarget": {
        "x": 8,
        "y": 1,
        "z": 8
      }
    }
  ],
  "requiredPermissions": [
    "ALLOW_TO_TRIGGER_AVATAR_EMOTE",
    "ALLOW_TO_MOVE_PLAYER_INSIDE_SCENE"
  ],
  "featureToggles": {}
}